rabbit_rpc/__init__.py
rabbit_rpc/base.py
rabbit_rpc/client.py
rabbit_rpc/consumer.py
rabbit_rpc/exceptions.py
rabbit_rpc/main.py
rabbit_rpc/queue.py
rabbit_rpc/server.py
rabbit_rpc/commands/__init__.py
rabbit_rpc/commands/base.py
rabbit_rpc/commands/worker.py
rabbit_rpc-0.0.2.dist-info/METADATA
rabbit_rpc-0.0.2.dist-info/RECORD
rabbit_rpc-0.0.2.dist-info/WHEEL
rabbit_rpc-0.0.2.dist-info/entry_points.txt
rabbit_rpc-0.0.2.dist-info/top_level.txt
