Metadata-Version: 2.1
Name: rabbit-rpc
Version: 0.0.2
Summary: A simple rpc client/server library
Home-page: https://github.com/MidTin/rabbit-rpc
Author: midtin
Author-email: midtin@gmail.com
License: MIT
Platform: UNKNOWN
Classifier: License :: OSI Approved :: MIT License
Classifier: Programming Language :: Python :: 2
Classifier: Programming Language :: Python :: 2.7
Classifier: Programming Language :: Python :: Implementation :: CPython
Requires-Dist: futures (==3.2.0)
Requires-Dist: pika (==0.11.2)
Requires-Dist: six
